gggifcheck/__init__.py
gggifcheck/fields.py
gggifcheck/items.py
gggifcheck/scrapy_ifcheck.py
gggifcheck-0.0.5.dist-info/LICENSE
gggifcheck-0.0.5.dist-info/METADATA
gggifcheck-0.0.5.dist-info/WHEEL
gggifcheck-0.0.5.dist-info/top_level.txt
gggifcheck-0.0.5.dist-info/RECORD
