Metadata-Version: 2.1
Name: gggifcheck
Version: 0.0.5
Summary: 通用条目字段检查，适应于各种场景的使用。
Home-page: https://github.com/kusen-alpha/gggifcheck
Author: kusen
Author-email: hu1194542196@qq.com
License: MIT
Project-URL: Bug Tracker, https://github.com/kusen-alpha/gggifcheck/issues
Project-URL: Documentation, https://github.com/kusen-alpha/gggifcheck/blob/master/README.md
Project-URL: Source Code, https://github.com/kusen-alpha/gggifcheck
Platform: any
Classifier: Programming Language :: Python :: 3
Classifier: License :: OSI Approved :: MIT License
Classifier: Operating System :: OS Independent
License-File: LICENSE
